{"avg_train_loss": 0.1939688694382034, "avg_test_loss": 0.18304140014820788, "timestamp": 1724679527, "checkpoint_dir_name": null, "done": true, "training_iteration": 1, "trial_id": "3e493_00018", "date": "2024-08-26_06-38-47", "time_this_iter_s": 107.50533533096313, "time_total_s": 107.50533533096313, "pid": 1990080, "hostname": "yen16", "node_ip": "10.112.2.45", "config": {"continuous_dim": 151, "hidden_dim": 15, "num_layers": 3, "num_embeddings": 17402, "embedding_dim": 3, "dropout_rate": 0.29, "lr": 1.8333910628872315e-06, "weight_decay": 1.144804873249583e-06, "num_epochs": 50, "num_gpus": 0, "batch_size": 32}, "time_since_restore": 107.50533533096313, "iterations_since_restore": 1}
